douban.py
setup.py
douban.egg-info/PKG-INFO
douban.egg-info/SOURCES.txt
douban.egg-info/dependency_links.txt
douban.egg-info/top_level.txt