Metadata-Version: 1.0
Name: douban
Version: 0.0.1
Summary: douban egg
Home-page: http://liluo.org
Author: liluo
Author-email: i@liluo.org
License: MIT License
Keywords: douban
Platform: any
